serdio/__init__.py
serdio/_test_utils.py
serdio/io_lifter.py
serdio/io_lifter_test.py
serdio/serde.py
serdio/serde_test.py
serdio-3.1.1.dist-info/LICENSE
serdio-3.1.1.dist-info/METADATA
serdio-3.1.1.dist-info/NOTICE
serdio-3.1.1.dist-info/WHEEL
serdio-3.1.1.dist-info/top_level.txt
serdio-3.1.1.dist-info/RECORD
