Metadata-Version: 2.1
Name: serdio
Version: 3.1.1
Summary: Automatic serialization of function inputs and outputs using MessagePack.
Author-email: Cape Privacy <contact@capeprivacy.com>
License: Apache License
Project-URL: repository, https://github.com/capeprivacy/pycape
Classifier: Programming Language :: Python
Requires-Python: >=3.7
License-File: LICENSE
License-File: NOTICE
Requires-Dist: msgpack
